bambird/__init__.py
bambird/cluster.py
bambird/config.py
bambird/dataset.py
bambird/features.py
bambird/segmentation.py
bambird/segmentation_extract_rois_core.py
bambird/segmentation_extract_rois_full_sig.py
bambird/version.py
bambird-0.3.0.dist-info/LICENSE
bambird-0.3.0.dist-info/METADATA
bambird-0.3.0.dist-info/WHEEL
bambird-0.3.0.dist-info/top_level.txt
bambird-0.3.0.dist-info/RECORD
