Metadata-Version: 2.1
Name: bambird
Version: 0.3.0
Summary: BAM, unsupervised labelling function to extract and cluster similar animal vocalizations together
Home-page: https://github.com/ear-team/bambird
Author: Felix Michaud and Sylvain Haupert
Author-email: felixmichaudlnhrdt@gmail.com, sylvain.haupert@mnhn.fr
Maintainer: Felix Michaud and Sylvain Haupert
License: BSD 3 Clause
Keywords: ecoacoustics,bioacoustics,ecology,dataset,signal processing,segmentation,features,clustering,unsupervised  labelling,deep learning,machine learning
Classifier: Development Status :: 4 - Beta
Classifier: Intended Audience :: Science/Research
Classifier: License :: OSI Approved :: BSD License
Classifier: Operating System :: OS Independent
Classifier: Programming Language :: Python :: 3.5
Classifier: Programming Language :: Python :: 3.6
Classifier: Programming Language :: Python :: 3.7
Classifier: Programming Language :: Python :: 3.8
Classifier: Topic :: Scientific/Engineering :: Artificial Intelligence
Requires-Python: >=3.5
License-File: LICENSE
Requires-Dist: scikit-image (>=0.19.2)
Requires-Dist: scikit-maad (>=1.3.12)
Requires-Dist: librosa (>=0.8.0)
Requires-Dist: scikit-learn (>=1.0)
Requires-Dist: hdbscan
Requires-Dist: matplotlib
Requires-Dist: umap-learn
Requires-Dist: tqdm
Requires-Dist: kneed
Requires-Dist: pyyaml
